<?xml version="1.0" encoding="UTF-8"?>
<gresources>
  <gresource prefix="/org/gnome/todo">
    <file alias="gtk/menus.ui">gtk/menus.ui</file>
    <file compressed="true" preprocess="xml-stripblanks">ui/edit-pane.ui</file>
    <file compressed="true" preprocess="xml-stripblanks">ui/goa-row.ui</file>
    <file compressed="true" preprocess="xml-stripblanks">ui/initial-setup.ui</file>
    <file compressed="true" preprocess="xml-stripblanks">ui/list-view.ui</file>
    <file compressed="true" preprocess="xml-stripblanks">ui/source-dialog.ui</file>
    <file compressed="true" preprocess="xml-stripblanks">ui/task-list-item.ui</file>
    <file compressed="true" preprocess="xml-stripblanks">ui/task-row.ui</file>
    <file compressed="true" preprocess="xml-stripblanks">ui/window.ui</file>
    <file compressed="true">theme/Adwaita.css</file>
    <file compressed="true">theme/bg.png</file>
    <file compressed="true">theme/bg.svg</file>
  </gresource>
</gresources>
